nonebot_plugin_strman/__init__.py
nonebot_plugin_strman/config.py
nonebot_plugin_strman/parser.py
nonebot_plugin_strman-1.2.0.dist-info/LICENSE
nonebot_plugin_strman-1.2.0.dist-info/WHEEL
nonebot_plugin_strman-1.2.0.dist-info/METADATA
nonebot_plugin_strman-1.2.0.dist-info/RECORD
