Metadata-Version: 2.1
Name: nonebot-plugin-strman
Version: 1.2.0
Summary: A string management tool for NoneBot 2
License: MIT
Author: Satoshi Jek
Author-email: jks15satoshi@gmail.com
Requires-Python: >=3.8,<4.0
Classifier: License :: OSI Approved :: MIT License
Classifier: Programming Language :: Python :: 3
Classifier: Programming Language :: Python :: 3.8
Classifier: Programming Language :: Python :: 3.9
Classifier: Programming Language :: Python :: 3.10
Requires-Dist: nonebot2 (>=2.0.0-rc.1,<3.0.0)
